LICENSE
README.md
setup.py
gittle/__init__.py
gittle/auth.py
gittle/exceptions.py
gittle/gittle.py
gittle/server.py
gittle.egg-info/PKG-INFO
gittle.egg-info/SOURCES.txt
gittle.egg-info/dependency_links.txt
gittle.egg-info/requires.txt
gittle.egg-info/top_level.txt
gittle/utils/__init__.py
gittle/utils/git.py
gittle/utils/paths.py
gittle/utils/urls.py