Metadata-Version: 1.0
Name: gittle
Version: 0.2.1
Summary: A high level pure python git implementation
Home-page: https://github.com/FriendCode/gittle
Author: Aaron O'Mullan
Author-email: aaron@friendco.de
License: MIT
Keywords: git dulwich pure python gittle
Platform: UNKNOWN
